yamlbundler/__init__.py
yamlbundler/__main__.py
yamlbundler/command.py
yamlbundler/exception.py
yamlbundler/include.py
yamlbundler/util.py
yamlbundler-0.0.1.dist-info/entry_points.txt
yamlbundler-0.0.1.dist-info/METADATA
yamlbundler-0.0.1.dist-info/WHEEL
yamlbundler-0.0.1.dist-info/RECORD
