Metadata-Version: 2.1
Name: yamlbundler
Version: 0.0.1
Summary: 
Author: dr666m1
Author-email: skndr666m1@gmail.com
Requires-Python: >=3.11,<4.0
Classifier: Programming Language :: Python :: 3
Classifier: Programming Language :: Python :: 3.11
Requires-Dist: jsonpath-ng (>=1.5.3,<2.0.0)
Requires-Dist: pyyaml (>=6.0,<7.0)
